<?xml version="1.0" encoding="UTF-8" standalone="yes"?><w:hdr xmlns:mc="http://schemas.openxmlformats.org/markup-compatibility/2006" xmlns:o="urn:schemas-microsoft-com:office:office" xmlns:r="http://schemas.openxmlformats.org/officeDocument/2006/relationships" xmlns:m="http://schemas.openxmlformats.org/officeDocument/2006/math" xmlns:v="urn:schemas-microsoft-com:vml" xmlns:wp="http://schemas.openxmlformats.org/drawingml/2006/wordprocessingDrawing" xmlns:w10="urn:schemas-microsoft-com:office:word" xmlns:w="http://schemas.openxmlformats.org/wordprocessingml/2006/main" xmlns:wne="http://schemas.microsoft.com/office/word/2006/wordml" xmlns:sl="http://schemas.openxmlformats.org/schemaLibrary/2006/main" xmlns:a="http://schemas.openxmlformats.org/drawingml/2006/main" xmlns:pic="http://schemas.openxmlformats.org/drawingml/2006/picture" xmlns:c="http://schemas.openxmlformats.org/drawingml/2006/chart" xmlns:lc="http://schemas.openxmlformats.org/drawingml/2006/lockedCanvas" xmlns:dgm="http://schemas.openxmlformats.org/drawingml/2006/diagram" xmlns:wps="http://schemas.microsoft.com/office/word/2010/wordprocessingShape" xmlns:wpg="http://schemas.microsoft.com/office/word/2010/wordprocessingGroup" xmlns:w14="http://schemas.microsoft.com/office/word/2010/wordml" xmlns:w15="http://schemas.microsoft.com/office/word/2012/wordml"><w:p w:rsidR="00000000" w:rsidDel="00000000" w:rsidP="00000000" w:rsidRDefault="00000000" w:rsidRPr="00000000" w14:paraId="0000004A"><w:pPr><w:jc w:val="both"/><w:rPr><w:i w:val="1"/><w:sz w:val="20"/><w:szCs w:val="20"/></w:rPr></w:pPr><w:r w:rsidDel="00000000" w:rsidR="00000000" w:rsidRPr="00000000"><w:rPr><w:rtl w:val="0"/></w:rPr></w:r><w:r w:rsidDel="00000000" w:rsidR="00000000" w:rsidRPr="00000000"><w:drawing><wp:anchor allowOverlap="1" behindDoc="0" distB="114300" distT="114300" distL="114300" distR="114300" hidden="0" layoutInCell="1" locked="0" relativeHeight="0" simplePos="0"><wp:simplePos x="0" y="0"/><wp:positionH relativeFrom="column"><wp:posOffset>6099900</wp:posOffset></wp:positionH><wp:positionV relativeFrom="paragraph"><wp:posOffset>247650</wp:posOffset></wp:positionV><wp:extent cx="952500" cy="952500"/><wp:effectExtent b="0" l="0" r="0" t="0"/><wp:wrapSquare wrapText="bothSides" distB="114300" distT="114300" distL="114300" distR="114300"/><wp:docPr descr="sena.png" id="1" name="image1.png"/><a:graphic><a:graphicData uri="http://schemas.openxmlformats.org/drawingml/2006/picture"><pic:pic><pic:nvPicPr><pic:cNvPr descr="sena.png" id="0" name="image1.png"/><pic:cNvPicPr preferRelativeResize="0"/></pic:nvPicPr><pic:blipFill><a:blip r:embed="rId1"><a:alphaModFix amt="70000"/></a:blip><a:srcRect b="0" l="0" r="0" t="0"/><a:stretch><a:fillRect/></a:stretch></pic:blipFill><pic:spPr><a:xfrm><a:off x="0" y="0"/><a:ext cx="952500" cy="952500"/></a:xfrm><a:prstGeom prst="rect"/><a:ln/></pic:spPr></pic:pic></a:graphicData></a:graphic></wp:anchor></w:drawing></w:r></w:p><w:p w:rsidR="00000000" w:rsidDel="00000000" w:rsidP="00000000" w:rsidRDefault="00000000" w:rsidRPr="00000000" w14:paraId="0000004B"><w:pPr><w:widowControl w:val="0"/><w:spacing w:line="240" w:lineRule="auto"/><w:jc w:val="center"/><w:rPr><w:i w:val="1"/><w:sz w:val="20"/><w:szCs w:val="20"/></w:rPr></w:pPr><w:r w:rsidDel="00000000" w:rsidR="00000000" w:rsidRPr="00000000"><w:rPr><w:rtl w:val="0"/></w:rPr></w:r></w:p><w:p w:rsidR="00000000" w:rsidDel="00000000" w:rsidP="00000000" w:rsidRDefault="00000000" w:rsidRPr="00000000" w14:paraId="0000004C"><w:pPr><w:jc w:val="both"/><w:rPr><w:i w:val="1"/><w:sz w:val="20"/><w:szCs w:val="20"/></w:rPr></w:pPr><w:r w:rsidDel="00000000" w:rsidR="00000000" w:rsidRPr="00000000"><w:rPr><w:rtl w:val="0"/></w:rPr></w:r></w:p><w:p w:rsidR="00000000" w:rsidDel="00000000" w:rsidP="00000000" w:rsidRDefault="00000000" w:rsidRPr="00000000" w14:paraId="0000004D"><w:pPr><w:widowControl w:val="0"/><w:spacing w:line="240" w:lineRule="auto"/><w:ind w:left="0" w:firstLine="0"/><w:rPr><w:i w:val="1"/><w:color w:val="666666"/><w:sz w:val="20"/><w:szCs w:val="20"/></w:rPr></w:pPr><w:r w:rsidDel="00000000" w:rsidR="00000000" w:rsidRPr="00000000"><w:rPr><w:i w:val="1"/><w:color w:val="666666"/><w:sz w:val="20"/><w:szCs w:val="20"/><w:rtl w:val="0"/></w:rPr><w:t xml:space="preserve">Programación de software. </w:t></w:r></w:p><w:p w:rsidR="00000000" w:rsidDel="00000000" w:rsidP="00000000" w:rsidRDefault="00000000" w:rsidRPr="00000000" w14:paraId="0000004E"><w:pPr><w:widowControl w:val="0"/><w:spacing w:line="240" w:lineRule="auto"/><w:ind w:left="0" w:firstLine="0"/><w:rPr><w:i w:val="1"/><w:color w:val="666666"/><w:sz w:val="20"/><w:szCs w:val="20"/></w:rPr></w:pPr><w:r w:rsidDel="00000000" w:rsidR="00000000" w:rsidRPr="00000000"><w:rPr><w:i w:val="1"/><w:color w:val="666666"/><w:sz w:val="20"/><w:szCs w:val="20"/><w:rtl w:val="0"/></w:rPr><w:t xml:space="preserve">Centro de Comercio y Turismo. </w:t></w:r></w:p><w:p w:rsidR="00000000" w:rsidDel="00000000" w:rsidP="00000000" w:rsidRDefault="00000000" w:rsidRPr="00000000" w14:paraId="0000004F"><w:pPr><w:widowControl w:val="0"/><w:spacing w:line="240" w:lineRule="auto"/><w:ind w:left="0" w:firstLine="0"/><w:rPr><w:i w:val="1"/><w:color w:val="666666"/><w:sz w:val="20"/><w:szCs w:val="20"/></w:rPr></w:pPr><w:r w:rsidDel="00000000" w:rsidR="00000000" w:rsidRPr="00000000"><w:rPr><w:i w:val="1"/><w:color w:val="666666"/><w:sz w:val="20"/><w:szCs w:val="20"/><w:rtl w:val="0"/></w:rPr><w:t xml:space="preserve">Regional Quindío. 2021</w:t></w:r></w:p><w:p w:rsidR="00000000" w:rsidDel="00000000" w:rsidP="00000000" w:rsidRDefault="00000000" w:rsidRPr="00000000" w14:paraId="00000050"><w:pPr><w:widowControl w:val="0"/><w:spacing w:line="240" w:lineRule="auto"/><w:ind w:left="0" w:firstLine="0"/><w:rPr><w:i w:val="1"/><w:color w:val="666666"/><w:sz w:val="20"/><w:szCs w:val="20"/></w:rPr></w:pPr><w:r w:rsidDel="00000000" w:rsidR="00000000" w:rsidRPr="00000000"><w:rPr><w:i w:val="1"/><w:color w:val="666666"/><w:sz w:val="20"/><w:szCs w:val="20"/><w:rtl w:val="0"/></w:rPr><w:t xml:space="preserve">Instructor: Germán Alberto Angarita Henao</w:t></w:r></w:p></w:hdr>